sz1/__init__.py
sz1/sz_utils.py
sz_utils-0.7.dist-info/LICENSE
sz_utils-0.7.dist-info/METADATA
sz_utils-0.7.dist-info/WHEEL
sz_utils-0.7.dist-info/top_level.txt
sz_utils-0.7.dist-info/RECORD
