Metadata-Version: 2.1
Name: sz-utils
Version: 0.7
Summary: A simple example library
Home-page: https://github.com/PeterouZh
Author: Peng Zhou
Author-email: zhoupeng23@nuaa.edu.cn
Classifier: Programming Language :: Python :: 3
Classifier: License :: OSI Approved :: MIT License
Classifier: Operating System :: OS Independent
License-File: LICENSE
Requires-Dist: numpy
